ai/__init__.py
ai/salmonbrain/__init__.py
ai/salmonbrain/params.py
ai/salmonbrain/ruleofthumb.py
dead_salmon_brain-0.0.7.dist-info/LICENSE
dead_salmon_brain-0.0.7.dist-info/METADATA
dead_salmon_brain-0.0.7.dist-info/WHEEL
dead_salmon_brain-0.0.7.dist-info/top_level.txt
dead_salmon_brain-0.0.7.dist-info/RECORD
