Metadata-Version: 2.1
Name: dead-salmon-brain
Version: 0.0.7
Summary: Dead Salmon Brain is a cluster computing system for analysing A/B experiments
Author: Dead Salmon Brain
Author-email: deadsalmonbrain@gmail.com
License: Apache License v2.0
Project-URL: Source code, https://github.com/Salmon-Brain/dead-salmon-brain/tree/main/python
Classifier: Programming Language :: Python :: 3
Classifier: License :: OSI Approved :: Apache Software License
Requires-Python: >=3.6
License-File: LICENSE
Requires-Dist: pyspark (>=2.3.0)
Requires-Dist: numpy
